astronomer_registry_cleanup/__init__.py
astronomer_registry_cleanup/cleanup.py
astronomer_registry_cleanup/main.py
astronomer_registry_cleanup/registry.py
astronomer_registry_cleanup-0.1.3.dist-info/METADATA
astronomer_registry_cleanup-0.1.3.dist-info/WHEEL
astronomer_registry_cleanup-0.1.3.dist-info/entry_points.txt
astronomer_registry_cleanup-0.1.3.dist-info/licenses/LICENSE
astronomer_registry_cleanup-0.1.3.dist-info/RECORD
