Metadata-Version: 2.4
Name: astronomer-registry-cleanup
Version: 0.1.3
Summary: A command-line tool for managing Docker registry cleanup operations in Astronomer environments
License: All Rights Reserved
License-File: LICENSE
Classifier: Development Status :: 3 - Alpha
Classifier: Environment :: Console
Classifier: Intended Audience :: Developers
Classifier: Intended Audience :: System Administrators
Classifier: Operating System :: OS Independent
Classifier: Programming Language :: Python :: 3
Classifier: Programming Language :: Python :: 3.10
Classifier: Programming Language :: Python :: 3.11
Classifier: Programming Language :: Python :: 3.12
Classifier: Programming Language :: Python :: 3.13
Classifier: Topic :: Software Development :: Libraries :: Python Modules
Classifier: Topic :: System :: Systems Administration
Classifier: Topic :: Utilities
Requires-Python: >=3.10
Requires-Dist: cryptography>=45.0.6
Requires-Dist: docker-registry-client>=0.5.2
Requires-Dist: docker>=7.1.0
Requires-Dist: pyjwt>=2.10.1
Requires-Dist: requests>=2.32.5
Provides-Extra: dev
Requires-Dist: ruff; extra == 'dev'
Provides-Extra: k8s
Requires-Dist: kubernetes; extra == 'k8s'
